{
    "version": "0.6.0",
    "description": "addrb: A lightweight CLI / TUI address book that supports CardDAV",
    "homepage": "https://github.com/mrusme/addrb",
    "license": "GPL-3.0-or-later",
    "architecture": {
        "64bit": {
            "url": "https://github.com/mrusme/addrb/releases/download/v0.6.0/addrb_0.6.0_windows_amd64.tar.gz",
            "hash": "23001cf3c3a2e71683fe16bf79d2cd40e4fd32528be62d815bbe039a99db5a67"
        },
        "32bit": {
            "url": "https://github.com/mrusme/addrb/releases/download/v0.6.0/addrb_0.6.0_windows_386.tar.gz",
            "hash": "a416f67bfd1f1007663f893406cba2fe3d34bf5103cee9ff1cf51544200a3f0d"
        },
        "arm64": {
            "url": "https://github.com/mrusme/addrb/releases/download/v0.6.0/addrb_0.6.0_windows_arm64.tar.gz",
            "hash": "49726889219ea8fc5057bbdc0025306ee2e3a38840d53e8f8c44dcf2a9f2c081"
        }
    },
    "bin": "addrb.exe",
    "checkver": "github",
    "autoupdate": {
        "architecture": {
            "64bit": {
                "url": "https://github.com/mrusme/addrb/releases/download/v$version/addrb_$version_windows_amd64.tar.gz"
            },
            "32bit": {
                "url": "https://github.com/mrusme/addrb/releases/download/v$version/addrb_$version_windows_386.tar.gz"
            },
            "arm64": {
                "url": "https://github.com/mrusme/addrb/releases/download/v$version/addrb_$version_windows_arm64.tar.gz"
            }
        },
        "hash": {
            "url": "$baseurl/addrb_$version_checksums.txt"
        }
    }
}
