{
    "version": "1.37.2",
    "description": "A light desktop tun proxy client powered by clash",
    "homepage": "https://igoogolx.github.io/lux-docs/docs/intro",
    "license": "GPL-3.0-or-later",
    "url": "https://github.com/igoogolx/lux/releases/download/v1.37.2/lux-1.37.2-windows-setup.exe",
    "hash": "0474480c418f33812a8057b4a32768c1c5b9df8e556b46b54efb94ebf36d1fd3",
    "innosetup": true,
    "shortcuts": [
        [
            "lux.exe",
            "Lux"
        ]
    ],
    "checkver": {
        "github": "https://github.com/igoogolx/lux"
    },
    "autoupdate": {
        "url": "https://github.com/igoogolx/lux/releases/download/v$version/lux-$version-windows-setup.exe",
        "hash": {
            "url": "$baseurl/checksum.txt",
            "regex": "$sha256"
        }
    }
}
