{
    "version": "1.20.2",
    "description": "A light desktop tun proxy client powered by clash",
    "homepage": "https://igoogolx.github.io/lux-docs/docs/intro",
    "license": "GPL-3.0-or-later",
    "url": "https://github.com/igoogolx/lux/releases/download/v1.20.2/lux-1.20.2+1.20.2-windows-setup.exe",
    "hash": "0d8c8222b82aade4cc6ad1813bf31faa89d9988421aefe9e04b93b54eea3d1af",
    "innosetup": true,
    "shortcuts": [
        [
            "lux.exe",
            "Lux"
        ]
    ],
    "checkver": {
        "github": "https://github.com/igoogolx/lux"
    },
    "autoupdate": {
        "url": "https://github.com/igoogolx/lux/releases/download/v$version/lux-$version+$version-windows-setup.exe",
        "hash": {
            "url": "$baseurl/checksum.txt",
            "regex": "$sha256"
        }
    }
}
