{
    "version": "1.16.0",
    "description": "High performance, multi-platform VNC client and server",
    "homepage": "https://tigervnc.org",
    "license": "GPL-2.0-or-later",
    "architecture": {
        "64bit": {
            "url": "https://downloads.sourceforge.net/project/tigervnc/stable/1.16.0/tigervnc64-1.16.0.exe",
            "hash": "sha1:e2bb9d96d96038e765eaf03159913ffbca3d45f7"
        },
        "32bit": {
            "url": "https://downloads.sourceforge.net/project/tigervnc/stable/1.16.0/tigervnc-1.16.0.exe",
            "hash": "sha1:7a7c9bd48a3937510c915f0b52103e54f984542b"
        }
    },
    "innosetup": true,
    "shortcuts": [
        [
            "vncviewer.exe",
            "TigerVNC Viewer"
        ]
    ],
    "checkver": {
        "sourceforge": "tigervnc"
    },
    "autoupdate": {
        "architecture": {
            "64bit": {
                "url": "https://downloads.sourceforge.net/project/tigervnc/stable/$version/tigervnc64-$version.exe"
            },
            "32bit": {
                "url": "https://downloads.sourceforge.net/project/tigervnc/stable/$version/tigervnc-$version.exe"
            }
        }
    }
}
