{
    "version": "9684214385",
    "description": "Browse the Fediverse",
    "homepage": "https://tuba.geopjr.dev/",
    "license": "GPL-3.0-or-later",
    "url": "https://nightly.link/GeopJr/Tuba/actions/runs/9684214385/tuba_windows_portable.zip",
    "hash": "2d22f72131cbdb8aaab9152ab046df894d2572224ad1d2c632159dd86b36dba9",
    "shortcuts": [
        [
            "bin\\dev.geopjr.Tuba.exe",
            "Tuba"
        ]
    ],
    "checkver": {
        "url": "https://api.github.com/repos/GeopJr/Tuba/actions/workflows/msys2.yml/runs?status=success&per_page=1",
        "jsonpath": "$.workflow_runs[0].id"
    },
    "autoupdate": {
        "url": "https://nightly.link/GeopJr/Tuba/actions/runs/$version/tuba_windows_portable.zip"
    }
}
