{
    "version": "15800396499",
    "description": "Browse the Fediverse",
    "homepage": "https://tuba.geopjr.dev/",
    "license": "GPL-3.0-or-later",
    "url": "https://nightly.link/GeopJr/Tuba/actions/runs/15800396499/tuba_windows_portable.zip",
    "hash": "7296600d5a502373643fd3cec7d48afc647005bc6ef3f072f8fb91425c1a1b25",
    "shortcuts": [
        [
            "bin\\dev.geopjr.Tuba.exe",
            "Tuba"
        ]
    ],
    "checkver": {
        "url": "https://api.github.com/repos/GeopJr/Tuba/actions/workflows/msys2.yml/runs?status=success&per_page=1",
        "jsonpath": "$.workflow_runs[0].id"
    },
    "autoupdate": {
        "url": "https://nightly.link/GeopJr/Tuba/actions/runs/$version/tuba_windows_portable.zip"
    }
}
